Metadata-Version: 2.1
Name: one-sec-mail
Version: 1.0
Summary: Create a one-time mail to receive the message
Home-page: https://github.com/DaSh-More/OneSecMail
Author: DaSh-More
Author-email: danila-763@yandex.ru
License: MIT
Platform: any
Classifier: Development Status :: 4 - Beta
Classifier: Programming Language :: Python :: 3
License-File: LICENSE
